pgsynthdata/__init__.py
pgsynthdata/__main__.py
pgsynthdata/database.py
pgsynthdata/datagenerator.py
pgsynthdata/generators/__init__.py
pgsynthdata/generators/address_generator.py
pgsynthdata/generators/array_generator_utils.py
pgsynthdata/generators/array_numeric_generator.py
pgsynthdata/generators/binary_generator.py
pgsynthdata/generators/boolean_generator.py
pgsynthdata/generators/character_generator.py
pgsynthdata/generators/copy_generator.py
pgsynthdata/generators/datetime_generator.py
pgsynthdata/generators/enumerated_generator.py
pgsynthdata/generators/fk_generator.py
pgsynthdata/generators/generator_utils.py
pgsynthdata/generators/geometric_generator.py
pgsynthdata/generators/ignore_generator.py
pgsynthdata/generators/legacy/__init__.py
pgsynthdata/generators/legacy/bytea_generator.py
pgsynthdata/generators/legacy/date_generator.py
pgsynthdata/generators/legacy/generator_utils.py
pgsynthdata/generators/legacy/geometry_generator.py
pgsynthdata/generators/legacy/numeric_generator.py
pgsynthdata/generators/legacy/varchar_generator.py
pgsynthdata/generators/numeric_generator.py
pgsynthdata/generators/person_generator.py
pgsynthdata/generators/spatial_generator.py
pgsynthdata/main.py
pgsynthdata-1.0.1.dist-info/LICENSE
pgsynthdata-1.0.1.dist-info/WHEEL
pgsynthdata-1.0.1.dist-info/METADATA
pgsynthdata-1.0.1.dist-info/RECORD
